series_intro_recognizer/__init__.py
series_intro_recognizer/config.py
series_intro_recognizer/py.typed
series_intro_recognizer/helpers/cached_iterator.py
series_intro_recognizer/processors/audio_files.py
series_intro_recognizer/processors/audio_samples.py
series_intro_recognizer/services/best_offset_finder.py
series_intro_recognizer/services/interval_improver.py
series_intro_recognizer/services/offsets_calculator.py
series_intro_recognizer/services/correlator/async_correlator.py
series_intro_recognizer/services/correlator/correlator.py
series_intro_recognizer/services/correlator/fragments_normalizer.py
series_intro_recognizer/services/correlator/sync_correlator.py
series_intro_recognizer/tp/interval.py
series_intro_recognizer/tp/tp.py
series_intro_recognizer-1.0.5.dist-info/licenses/LICENSE
series_intro_recognizer-1.0.5.dist-info/METADATA
series_intro_recognizer-1.0.5.dist-info/WHEEL
series_intro_recognizer-1.0.5.dist-info/top_level.txt
series_intro_recognizer-1.0.5.dist-info/RECORD
