Metadata-Version: 2.4
Name: series_intro_recognizer
Version: 1.0.5
Summary: Find the intro of episodes of a series
Author: HRAshton
Project-URL: Homepage, https://github.com/HRAshton/SeriesIntroRecognizer
Project-URL: Documentation, https://github.com/HRAshton/SeriesIntroRecognizer/wiki/SeriesIntroRecognizer-%E2%80%90-Wiki
Project-URL: Issues, https://github.com/HRAshton/SeriesIntroRecognizer/issues
Classifier: Programming Language :: Python :: 3
Classifier: License :: OSI Approved :: MIT License
Classifier: Operating System :: OS Independent
Requires-Python: >=3.12
License-File: LICENSE
Requires-Dist: librosa>=0.10.1
Requires-Dist: numpy>=1.26.4
Requires-Dist: scikit-learn>=1.4.2
Requires-Dist: scipy>=1.13
Requires-Dist: setuptools>=69.2
Provides-Extra: dev
Requires-Dist: soundfile>=0.12.1; extra == "dev"
Requires-Dist: pytest>=8.1.1; extra == "dev"
Dynamic: license-file
